a_parser/__init__.py
a_parser-3.0.1.dist-info/LICENSE
a_parser-3.0.1.dist-info/METADATA
a_parser-3.0.1.dist-info/WHEEL
a_parser-3.0.1.dist-info/top_level.txt
a_parser-3.0.1.dist-info/RECORD
