Metadata-Version: 2.1
Name: a-parser
Version: 3.0.1
Summary: A-Parser API Module
Home-page: https://github.com/a-parser/api-python
Author: A-Parser
Author-email: support@a-parser.com
License: UNKNOWN
Platform: UNKNOWN
Classifier: Programming Language :: Python :: 3
Classifier: Programming Language :: Python :: 2
Classifier: License :: OSI Approved :: MIT License
Classifier: Operating System :: OS Independent
Requires-Python: >=3.8
